djangorestframework_camel_case/__init__.py
djangorestframework_camel_case/parser.py
djangorestframework_camel_case/render.py
djangorestframework_camel_case/settings.py
djangorestframework_camel_case/util.py
djangorestframework_camel_case_2-0.0.1.dist-info/LICENSE
djangorestframework_camel_case_2-0.0.1.dist-info/METADATA
djangorestframework_camel_case_2-0.0.1.dist-info/WHEEL
djangorestframework_camel_case_2-0.0.1.dist-info/top_level.txt
djangorestframework_camel_case_2-0.0.1.dist-info/RECORD
