Metadata-Version: 2.1
Name: djangorestframework-camel-case-2
Version: 0.0.1
Summary: Camel case JSON support for Django REST framework.
Home-page: https://github.com/canassa/djangorestframework-camel-case
Author: Cesar Canassa
Author-email: cesar.canassa@gmail.com
License: BSD
Keywords: djangorestframework_camel_case
Platform: UNKNOWN
Classifier: Development Status :: 2 - Pre-Alpha
Classifier: Intended Audience :: Developers
Classifier: License :: OSI Approved :: BSD License
Classifier: Natural Language :: English
Classifier: Programming Language :: Python :: 3
Classifier: Programming Language :: Python :: 3.6
Classifier: Programming Language :: Python :: 3.7
Provides-Extra: tests
Requires-Dist: pytest ; extra == 'tests'
Requires-Dist: flake8 ; extra == 'tests'
Requires-Dist: django ; extra == 'tests'
Requires-Dist: djangorestframework ; extra == 'tests'
